net_speed_monitor.py
net_speed_monitor-0.6.1.dist-info/LICENSE
net_speed_monitor-0.6.1.dist-info/METADATA
net_speed_monitor-0.6.1.dist-info/WHEEL
net_speed_monitor-0.6.1.dist-info/entry_points.txt
net_speed_monitor-0.6.1.dist-info/top_level.txt
net_speed_monitor-0.6.1.dist-info/RECORD
